rabboni/MUL1.py
rabboni/MUL10.py
rabboni/MUL11.py
rabboni/MUL2.py
rabboni/MUL3.py
rabboni/MUL4.py
rabboni/MUL5.py
rabboni/MUL6.py
rabboni/MUL7.py
rabboni/MUL8.py
rabboni/MUL9.py
rabboni/Rabboni.py
rabboni/__init__.py
Rabboni-2.0.dist-info/METADATA
Rabboni-2.0.dist-info/WHEEL
Rabboni-2.0.dist-info/top_level.txt
Rabboni-2.0.dist-info/RECORD
